setup.cfg
setup.py
sbsmanip/__init__.py
sbsmanip/cubeblocks.py
sbsmanip/io.py
sbsmanip/modifier.py
sbsmanip/sector.py
sbsmanip.egg-info/PKG-INFO
sbsmanip.egg-info/SOURCES.txt
sbsmanip.egg-info/dependency_links.txt
sbsmanip.egg-info/entry_points.txt
sbsmanip.egg-info/requires.txt
sbsmanip.egg-info/top_level.txt
segc/__init__.py
segc/app.py