Metadata-Version: 1.0
Name: sbsmanip
Version: 0.3.1
Summary: sbsmanip is a set of utilities designed to help clean a Space Engineers savefile for performance reasons
Home-page: https://github.com/vmrob/sbsmanip
Author: Victor Robertson
Author-email: victor.robertson.iv@gmail.com
License: MIT License
Platform: UNKNOWN
